fast_gat/GAT.py
fast_gat/__init__.py
fast_gat/dense_gat.py
fast_gat/graph_util.py
fast_gat/node_downsampler.py
fast_gat/node_upsampler.py
fast_gat-0.2.0.dist-info/LICENSE
fast_gat-0.2.0.dist-info/METADATA
fast_gat-0.2.0.dist-info/WHEEL
fast_gat-0.2.0.dist-info/top_level.txt
fast_gat-0.2.0.dist-info/RECORD
