Metadata-Version: 2.1
Name: fast-gat
Version: 0.2.0
Summary: A PyTorch implementation of Graph Attention Networks, with experimental speedup features.
Home-page: https://github.com/tatp22/pytorch-fast-GAT
Author: Peter Tatkowski
Author-email: tatp22@gmail.com
License: UNKNOWN
Keywords: attention,deep learning,artificial intelligence,sparse attention
Platform: UNKNOWN
Classifier: Programming Language :: Python :: 3
Classifier: License :: OSI Approved :: MIT License
Classifier: Topic :: Scientific/Engineering :: Artificial Intelligence
License-File: LICENSE
Requires-Dist: torch
